dvsportal/__init__.py
dvsportal/__version__.py
dvsportal/const.py
dvsportal/dvsportal.py
dvsportal/exceptions.py
dvsportal/py.typed
dvsportal-1.3.2.dist-info/METADATA
dvsportal-1.3.2.dist-info/WHEEL
dvsportal-1.3.2.dist-info/RECORD
