Metadata-Version: 2.1
Name: dvsportal
Version: 1.3.2
Summary: Asynchronous Python client for the DVSPortal API as used by Dutch muncipalities for guest parking.
Author: ChessSpider
Author-email: chessspider@gmail.com
Requires-Python: >=3.10,<4.0
Classifier: Programming Language :: Python :: 3
Classifier: Programming Language :: Python :: 3.10
Classifier: Programming Language :: Python :: 3.11
Classifier: Programming Language :: Python :: 3.12
Requires-Dist: aiohttp (>=3.9.3,<4.0.0)
Requires-Dist: yarl (>=1.9.4,<2.0.0)
